structlog_extensions/__init__.py
structlog_extensions/processors.py
structlog_extensions/utils.py
structlog_extensions_nralbers-1.0.4.dist-info/LICENSE
structlog_extensions_nralbers-1.0.4.dist-info/METADATA
structlog_extensions_nralbers-1.0.4.dist-info/WHEEL
structlog_extensions_nralbers-1.0.4.dist-info/top_level.txt
structlog_extensions_nralbers-1.0.4.dist-info/RECORD
