Metadata-Version: 2.1
Name: structlog-extensions-nralbers
Version: 1.0.4
Summary: Processors for Structlog library
Home-page: https://structlog-extensions-nralbers.readthedocs.io/en/latest/
Author: Niels Albers
Author-email: nralbers@gmail.com
License: MIT
Project-URL: Documentation, https://structlog-extensions-nralbers.readthedocs.io/en/latest/
Project-URL: Source, https://github.com/nralbers/structlog-extensions-nralbers
Project-URL: Tracker, https://github.com/nralbers/structlog-extensions-nralbers/issues
Keywords: logging,structured,structure,log,ecs,apache-combined-log
Platform: UNKNOWN
Classifier: Natural Language :: English
Classifier: Programming Language :: Python :: 3
Classifier: Programming Language :: Python :: 3.6
Classifier: Programming Language :: Python :: 3.7
Classifier: Programming Language :: Python :: 3.8
Classifier: Programming Language :: Python :: Implementation :: CPython
Classifier: Programming Language :: Python :: Implementation :: PyPy
Classifier: License :: OSI Approved :: MIT License
Classifier: Operating System :: OS Independent
Classifier: Development Status :: 5 - Production/Stable
Classifier: Topic :: Software Development :: Libraries :: Python Modules
Classifier: Intended Audience :: Developers
Requires-Python: ~=3.5
License-File: LICENSE
Requires-Dist: structlog (>=19.2)
Requires-Dist: user-agents
Requires-Dist: deepmerge
Requires-Dist: pytz
